dffml_source_mysql/__init__.py
dffml_source_mysql/db.py
dffml_source_mysql/source.py
dffml_source_mysql/version.py
dffml_source_mysql/util/__init__.py
dffml_source_mysql/util/mysql_docker.py
tests/__init__.py
tests/test_db.py
tests/test_source.py
dffml_source_mysql-0.1.0.post0.dist-info/LICENSE
dffml_source_mysql-0.1.0.post0.dist-info/METADATA
dffml_source_mysql-0.1.0.post0.dist-info/WHEEL
dffml_source_mysql-0.1.0.post0.dist-info/entry_points.txt
dffml_source_mysql-0.1.0.post0.dist-info/top_level.txt
dffml_source_mysql-0.1.0.post0.dist-info/RECORD
